ibmpairs/authentication.py
ibmpairs/catalog.py
ibmpairs/client.py
ibmpairs/common.py
ibmpairs/config.py
ibmpairs/constants.py
ibmpairs/dashboard.py
ibmpairs/logger.py
ibmpairs/messages.py
ibmpairs/paw.py
ibmpairs/query.py
ibmpairs/upload.py
ibmpairs/utils.py
ibmpairs/version.py
ibmpairs/external/ibm.py
ibmpairs-3.1.14.dist-info/LICENSE
ibmpairs-3.1.14.dist-info/METADATA
ibmpairs-3.1.14.dist-info/WHEEL
ibmpairs-3.1.14.dist-info/top_level.txt
ibmpairs-3.1.14.dist-info/RECORD
