Metadata-Version: 2.1
Name: ibmpairs
Version: 3.1.14
Summary: open source Python modules for the IBM Environmental Intelligence Geospatial APIs platform
Home-page: https://ibm.github.io/ibmpairs/
Author: Environmental Intelligence, IBM Software
Author-email: pairs@us.ibm.com
Maintainer: taylorsteffanj
License: BSD-Clause-3
Project-URL: Documentation, https://ibm.github.io/ibmpairs/
Project-URL: Source, https://github.com/ibm/ibmpairs
Project-URL: Tracker, https://github.com/ibm/ibmpairs/issues
Keywords: IBM Environmental Intelligence Geospatial APIs Geospatial Analytics PAIRS GIS BigGeoData
Classifier: Development Status :: 3 - Alpha
Classifier: License :: OSI Approved :: BSD License
Classifier: Programming Language :: Python :: 3
Classifier: Topic :: Scientific/Engineering :: GIS
License-File: LICENSE
Requires-Dist: aiohttp (>=3.0.0)
Requires-Dist: fs (>=2.4.16)
Requires-Dist: geojson
Requires-Dist: ibm-cos-sdk
Requires-Dist: jsonschema
Requires-Dist: numpy (>=1.18.1)
Requires-Dist: pandas (>=1.0.1)
Requires-Dist: Pillow (>=10.2.0)
Requires-Dist: polling
Requires-Dist: pytz
Requires-Dist: rasterio (>=1.4.3)
Requires-Dist: Requests (>=2.4)
Requires-Dist: Shapely
Requires-Dist: tableschema
